flask_nyc.py
Flask_NYC-0.1.1.dist-info/DESCRIPTION.rst
Flask_NYC-0.1.1.dist-info/METADATA
Flask_NYC-0.1.1.dist-info/pydist.json
Flask_NYC-0.1.1.dist-info/RECORD
Flask_NYC-0.1.1.dist-info/top_level.txt
Flask_NYC-0.1.1.dist-info/WHEEL
