Metadata-Version: 2.0
Name: Flask-NYC
Version: 0.1.1
Summary: New York Flask Meetup
Home-page: http://flask-nyc.org
Author: Andy Dirnberger
Author-email: dirn@dirnonline.com
License: UNKNOWN
Platform: UNKNOWN
Requires-Dist: flask (>=0.8)
